devvit_mgr/__init__.py
devvit_mgr/cli.py
devvit_mgr/const.py
devvit_mgr/manager.py
devvit_mgr/models.py
devvit_manager-1.0.1.dist-info/LICENSE.txt
devvit_manager-1.0.1.dist-info/METADATA
devvit_manager-1.0.1.dist-info/WHEEL
devvit_manager-1.0.1.dist-info/entry_points.txt
devvit_manager-1.0.1.dist-info/top_level.txt
devvit_manager-1.0.1.dist-info/RECORD
