Metadata-Version: 2.1
Name: devvit-manager
Version: 1.0.1
Summary: Devvit Manager is a Python package that enables you to easily utilize devvit with multiple Reddit user accounts.
Author: Joel Payne
Author-email: lilspazjoekp@gmail.com
License: Simplified BSD License
Keywords: devvit manager reddit
Classifier: Development Status :: 5 - Production/Stable
Classifier: Environment :: Console
Classifier: Intended Audience :: Developers
Classifier: License :: OSI Approved :: BSD License
Classifier: Natural Language :: English
Classifier: Operating System :: OS Independent
Classifier: Programming Language :: Python
Classifier: Programming Language :: Python :: 3
Classifier: Programming Language :: Python :: 3.8
Classifier: Programming Language :: Python :: 3.9
Classifier: Programming Language :: Python :: 3.10
Classifier: Programming Language :: Python :: 3.11
Classifier: Topic :: Utilities
Requires-Python: ~=3.8
License-File: LICENSE.txt
Requires-Dist: click (==8.*)
Requires-Dist: pick (==2.*)
Requires-Dist: praw (==7.*)
Provides-Extra: ci
Requires-Dist: docutils (==0.8.*) ; extra == 'ci'
Requires-Dist: packaging (==23.*) ; extra == 'ci'
Provides-Extra: dev
Requires-Dist: docutils (==0.8.*) ; extra == 'dev'
Requires-Dist: packaging (==23.*) ; extra == 'dev'
Requires-Dist: pre-commit ; extra == 'dev'
Provides-Extra: lint
Requires-Dist: pre-commit ; extra == 'lint'
